vibe_analyzer/__init__.py
vibe_analyzer/main.py
vibe_analyzer/prompts.py
vibe_analyzer-2025.12.21143555.dist-info/METADATA
vibe_analyzer-2025.12.21143555.dist-info/WHEEL
vibe_analyzer-2025.12.21143555.dist-info/top_level.txt
vibe_analyzer-2025.12.21143555.dist-info/RECORD
