Metadata-Version: 2.4
Name: vibe-analyzer
Version: 2025.12.21143555
Summary: A new package that analyzes user-provided text to detect and categorize the overall emotional tone or 'vibe' of the content. It processes input text and returns a structured summary of the detected em
Author-email: vibe-analyzer <hi@eugene.plus>
License: MIT
Project-URL: Homepage, https://github.com/chigwell/vibe-analyzer
Requires-Python: >=3.9
Requires-Dist: langchain-llm7>=0.0.0
Requires-Dist: llmatch-messages>=0.0.0
Requires-Dist: langchain-core>=0.3.0
